decord/logging.py
decord/libdecord.dylib
decord/video_reader.py
decord/video_loader.py
decord/_api_internal.py
decord/__init__.py
decord/ndarray.py
decord/base.py
decord/bridge/tf.py
decord/bridge/mxnet.py
decord/bridge/torchdl.py
decord/bridge/__init__.py
decord/bridge/utils.py
decord/bridge/tvm.py
decord/function/__init__.py
decord/function/base.py
decord/_ffi/__init__.py
decord/_ffi/libinfo.py
decord/_ffi/ndarray.py
decord/_ffi/runtime_ctypes.py
decord/_ffi/base.py
decord/_ffi/function.py
decord/_ffi/_cy2/__init__.py
decord/_ffi/_cy3/__init__.py
decord/_ffi/_ctypes/__init__.py
decord/_ffi/_ctypes/types.py
decord/_ffi/_ctypes/ndarray.py
decord/_ffi/_ctypes/function.py
decord/.dylibs/libavfilter.7.103.100.dylib
decord/.dylibs/libswresample.3.8.100.dylib
decord/.dylibs/libavutil.56.64.100.dylib
decord/.dylibs/libswscale.5.8.100.dylib
decord/.dylibs/libavcodec.58.122.100.dylib
decord/.dylibs/libvpx.6.dylib
decord/.dylibs/libpostproc.55.8.100.dylib
decord/.dylibs/libx264.161.dylib
decord/.dylibs/libavformat.58.67.100.dylib
decord/.dylibs/liblzma.5.dylib
decord/.dylibs/libavdevice.58.11.103.dylib
decord/data/__init__.py
decord/data/base_action.py
decord/data/dataloader.py
decord/data/kinetics/__init__.py
decord/data/kinetics/kinetics400_action.py
decord/data/transforms/__init__.py
decord/data/transforms/action.py
decord-0.5.2.dist-info/RECORD
decord-0.5.2.dist-info/WHEEL
decord-0.5.2.dist-info/top_level.txt
decord-0.5.2.dist-info/METADATA
